<resGP>
	<group>diningPhilosophers</group>
	<process>
	<resNP>
		<name>up1</name>
		<type>fup</type>
		<name>d1</name>
		<type>fdown</type>
		<name>d2</name>
		<type>fdown</type>
		<name>up2</name>
		<type>fup</type>
		<process>
		<parP>
			<process>
				<inExternal>
					<subj>think</subj>
					<obj>value</obj>
					<type>Integer</type>
					<process>
						<in>
						<subj>up1</subj>	
						<obj>fork</obj>
						<type>Integer</type>
							<process>
								<in>
									<subj>up2</subj>
									<obj>fork2</obj>
									<type>Integer</type>
									<process>
										<inExternal>
											<subj>eat</subj>
											<obj>value2</obj>
											<type>Integer</type>
												<process>
													<in>
														<subj>d1</subj>
														<obj>fork1</obj>
														<type>Integer</type>
														<process>
															<in>
																<subj>d2</subj>
																<obj>fork3</obj>
																<type>Integer</type>
																<process>
																	<Nil>0</Nil>
																</process>
															</in>
														</process>
													</in>
												</process>
											</inExternal>
										</process>
									</in>										
								</process>
							</in>
						</process>
					</inExternal>
			</process>
			<process>
				<inExternal>
					<subj>think9</subj>
					<obj>value9</obj>
					<type>Integer</type>
					<process>
						<in>
						<subj>up2</subj>	
						<obj>fork18</obj>
						<type>Integer</type>
						<process>
							<in>
								<subj>up1</subj>
								<obj>fork19</obj>
								<type>Integer</type>
								<process>
									<inExternal>
										<subj>eat9</subj>
										<obj>value9</obj>
										<type>Integer</type>
										<process>
											<in>
												<subj>d2</subj>
												<obj>fork20</obj>
												<type>Integer</type>
												<process>
													<in>
														<subj>d1</subj>
														<obj>fork21</obj>
														<type>Integer</type>
														<process>
															<Nil>0</Nil>
														</process>
													</in>
												</process>
											</in>
										</process>
									</inExternal>
								</process>
							</in>										
						</process>
					</in>
				</process>
				</inExternal>
			</process>
			<process>
				<out>
					<subj>u1</subj>
					<obj>f1</obj>
					<process>
						<out>
							<subj>d1</subj>
							<obj>f1</obj>
							<process>
								<Nil>0</Nil>
							</process>
						</out>
					</process>
				</out>			
			</process>
			<process>
				<out>
					<subj>u2</subj>
					<obj>f2</obj>
					<process>
						<out>
							<subj>d2</subj>
							<obj>f2</obj>
							<process>
								<Nil>0</Nil>
							</process>
						</out>
					</process>
				</out>
			</process>			
		</parP>
		</process>				
	</resNP>	
	</process>
</resGP>